{
    "data": [
    {
    "id": 1,
    "abbreviation": "ATL",
    "city": "Atlanta",
    "conference": "East",
    "division": "Southeast",
    "full_name": "Atlanta Hawks",
    "name": "Hawks",
    "logo": "LOGOS/ATL_LOGO.png",
    "oldLogo": "LOGOS/ATL_RETRO.webp"
    },
    {
    "id": 2,
    "abbreviation": "BOS",
    "city": "Boston",
    "conference": "East",
    "division": "Atlantic",
    "full_name": "Boston Celtics",
    "name": "Celtics",
    "logo": "LOGOS/BOS_LOGO.png",
    "oldLogo":"RETRO_LOGOS/BOS_RETRO.gif"

    },
    {
    "id": 3,
    "abbreviation": "BKN",
    "city": "Brooklyn",
    "conference": "East",
    "division": "Atlantic",
    "full_name": "Brooklyn Nets",
    "name": "Nets",
    "logo": "LOGOS/BKN_LOGO.png",
    "oldLogo":"RETRO_LOGOS/BKN_RETRO.png"
    },
    {
    "id": 4,
    "abbreviation": "CHA",
    "city": "Charlotte",
    "conference": "East",
    "division": "Southeast",
    "full_name": "Charlotte Hornets",
    "name": "Hornets",
    "logo": "LOGOS/CHA_LOGO.png",
    "oldLogo":"RETRO_LOGOS/CHA_RETRO.gif"
    },
    {
    "id": 5,
    "abbreviation": "CHI",
    "city": "Chicago",
    "conference": "East",
    "division": "Central",
    "full_name": "Chicago Bulls",
    "name": "Bulls",
    "logo": "LOGOS/CHI_LOGO.png",
    "oldLogo":"RETRO_LOGOS/CHI_RETRO.png"
    },
    {
    "id": 6,
    "abbreviation": "CLE",
    "city": "Cleveland",
    "conference": "East",
    "division": "Central",
    "full_name": "Cleveland Cavaliers",
    "name": "Cavaliers",
    "logo": "LOGOS/CLE_LOGO.png",
    "oldLogo":"RETRO_LOGOS/CLE_RETRO.png"
    },
    {
    "id": 7,
    "abbreviation": "DAL",
    "city": "Dallas",
    "conference": "West",
    "division": "Southwest",
    "full_name": "Dallas Mavericks",
    "name": "Mavericks",
    "logo": "LOGOS/DAL_LOGO.png",
    "oldLogo":"RETRO_LOGOS/DAL_RETRO.jpeg"
    },
    {
    "id": 8,
    "abbreviation": "DEN",
    "city": "Denver",
    "conference": "West",
    "division": "Northwest",
    "full_name": "Denver Nuggets",
    "name": "Nuggets",
    "logo": "LOGOS/DEN_LOGO.png",
    "oldLogo":"RETRO_LOGOS/DEN_RETRO.png"
    },
    {
    "id": 9,
    "abbreviation": "DET",
    "city": "Detroit",
    "conference": "East",
    "division": "Central",
    "full_name": "Detroit Pistons",
    "name": "Pistons",
    "logo": "LOGOS/DET_LOGO.png",
    "oldLogo":"RETRO_LOGOS/DET_RETRO.png"
    },
    {
    "id": 10,
    "abbreviation": "GSW",
    "city": "Golden State",
    "conference": "West",
    "division": "Pacific",
    "full_name": "Golden State Warriors",
    "name": "Warriors",
    "logo": "LOGOS/GSW_LOGO.png",
    "oldLogo":"RETRO_LOGOS/GSW_RETRO.png"
    },
    {
    "id": 11,
    "abbreviation": "HOU",
    "city": "Houston",
    "conference": "West",
    "division": "Southwest",
    "full_name": "Houston Rockets",
    "name": "Rockets",
    "logo": "LOGOS/HOU_LOGO.png",
    "oldLogo":"RETRO_LOGOS/HOU_RETRO.gif"
    },
    {
    "id": 12,
    "abbreviation": "IND",
    "city": "Indiana",
    "conference": "East",
    "division": "Central",
    "full_name": "Indiana Pacers",
    "name": "Pacers",
    "logo": "LOGOS/IND_LOGO.png",
    "oldLogo":"RETRO_LOGOS/IND_RETRO.jpeg"
    },
    {
    "id": 13,
    "abbreviation": "LAC",
    "city": "LA",
    "conference": "West",
    "division": "Pacific",
    "full_name": "LA Clippers",
    "name": "Clippers",
    "logo": "LOGOS/LAC_LOGO.png",
    "oldLogo":"RETRO_LOGOS/LAC_RETRO.png"
    },
    {
    "id": 14,
    "abbreviation": "LAL",
    "city": "Los Angeles",
    "conference": "West",
    "division": "Pacific",
    "full_name": "Los Angeles Lakers",
    "name": "Lakers",
    "logo": "LOGOS/LAL_LOGO.png",
    "oldLogo":"RETRO_LOGOS/LAL_RETRO.png"
    },
    {
    "id": 15,
    "abbreviation": "MEM",
    "city": "Memphis",
    "conference": "West",
    "division": "Southwest",
    "full_name": "Memphis Grizzlies",
    "name": "Grizzlies",
    "logo": "LOGOS/MEM_LOGO.png",
    "oldLogo":"RETRO_LOGOS/MEM_RETRO.png"
    },
    {
    "id": 16,
    "abbreviation": "MIA",
    "city": "Miami",
    "conference": "East",
    "division": "Southeast",
    "full_name": "Miami Heat",
    "name": "Heat",
    "logo": "LOGOS/MIA_LOGO.png",
    "oldLogo":"RETRO_LOGOS/MIA_RETRO.jpeg"
    },
    {
    "id": 17,
    "abbreviation": "MIL",
    "city": "Milwaukee",
    "conference": "East",
    "division": "Central",
    "full_name": "Milwaukee Bucks",
    "name": "Bucks",
    "logo": "LOGOS/MIL_LOGO.png",
    "oldLogo":"RETRO_LOGOS/MIL_RETRO.png"
    },
    {
    "id": 18,
    "abbreviation": "MIN",
    "city": "Minnesota",
    "conference": "West",
    "division": "Northwest",
    "full_name": "Minnesota Timberwolves",
    "name": "Timberwolves",
    "logo": "LOGOS/MIN_LOGO.png",
    "oldLogo":"RETRO_LOGOS/MIN_RETRO.png"
    },
    {
    "id": 19,
    "abbreviation": "NOP",
    "city": "New Orleans",
    "conference": "West",
    "division": "Southwest",
    "full_name": "New Orleans Pelicans",
    "name": "Pelicans",
    "logo": "LOGOS/NOP_LOGO.png",
    "oldLogo":"RETRO_LOGOS/NOP_RETRO.png"
    },
    {
    "id": 20,
    "abbreviation": "NYK",
    "city": "New York",
    "conference": "East",
    "division": "Atlantic",
    "full_name": "New York Knicks",
    "name": "Knicks",
    "logo": "LOGOS/NYK_LOGO.png",
    "oldLogo":"RETRO_LOGOS/NYK_RETRO.jpeg"
    },
    {
    "id": 21,
    "abbreviation": "OKC",
    "city": "Oklahoma City",
    "conference": "West",
    "division": "Northwest",
    "full_name": "Oklahoma City Thunder",
    "name": "Thunder",
    "logo": "LOGOS/OKC_LOGO.png",
    "oldLogo":"RETRO_LOGOS/OKC_RETRO.png"
    },
    {
    "id": 22,
    "abbreviation": "ORL",
    "city": "Orlando",
    "conference": "East",
    "division": "Southeast",
    "full_name": "Orlando Magic",
    "name": "Magic",
    "logo": "LOGOS/ORL_LOGO.png",
    "oldLogo":"RETRO_LOGOS/ORL_RETRO.png"
    },
    {
    "id": 23,
    "abbreviation": "PHI",
    "city": "Philadelphia",
    "conference": "East",
    "division": "Atlantic",
    "full_name": "Philadelphia 76ers",
    "name": "76ers",
    "logo": "LOGOS/PHI_LOGO.png",
    "oldLogo":"RETRO_LOGOS/PHI_RETRO.png"
    },
    {
    "id": 24,
    "abbreviation": "PHX",
    "city": "Phoenix",
    "conference": "West",
    "division": "Pacific",
    "full_name": "Phoenix Suns",
    "name": "Suns",
    "logo": "LOGOS/PHX_LOGO.png",
    "oldLogo":"RETRO_LOGOS/PHX_RETRO.jpeg"
    },
    {
    "id": 25,
    "abbreviation": "POR",
    "city": "Portland",
    "conference": "West",
    "division": "Northwest",
    "full_name": "Portland Trail Blazers",
    "name": "Trail Blazers",
    "logo": "LOGOS/POR_LOGO.png",
    "oldLogo":"RETRO_LOGOS/POR_RETRO.png"
    },
    {
    "id": 26,
    "abbreviation": "SAC",
    "city": "Sacramento",
    "conference": "West",
    "division": "Pacific",
    "full_name": "Sacramento Kings",
    "name": "Kings",
    "logo": "LOGOS/SAC_LOGO.png",
    "oldLogo":"RETRO_LOGOS/SAC_RETRO.jpg"
    },
    {
    "id": 27,
    "abbreviation": "SAS",
    "city": "San Antonio",
    "conference": "West",
    "division": "Southwest",
    "full_name": "San Antonio Spurs",
    "name": "Spurs",
    "logo": "LOGOS/SAS_LOGO.png",
    "oldLogo":"RETRO_LOGOS/SAS_RETRO.webp"
    },
    {
    "id": 28,
    "abbreviation": "TOR",
    "city": "Toronto",
    "conference": "East",
    "division": "Atlantic",
    "full_name": "Toronto Raptors",
    "name": "Raptors",
    "logo": "LOGOS/TOR_LOGO.png",
    "oldLogo":"RETRO_LOGOS/TOR_RETRO.png"
    },
    {
    "id": 29,
    "abbreviation": "UTA",
    "city": "Utah",
    "conference": "West",
    "division": "Northwest",
    "full_name": "Utah Jazz",
    "name": "Jazz",
    "logo": "LOGOS/UTA_LOGO.png",
    "oldLogo":"RETRO_LOGOS/UTA_RETRO.png"
    },
    {
    "id": 30,
    "abbreviation": "WAS",
    "city": "Washington",
    "conference": "East",
    "division": "Southeast",
    "full_name": "Washington Wizards",
    "name": "Wizards",
    "logo": "LOGOS/WAS_LOGO.png",
    "oldLogo":"RETRO_LOGOS/WAS_RETRO.png"
    }
    ],
    "meta": {
    "current_page": 1,
    "next_page": 2,
    "per_page": 30
    }
    }